{
    "body": [
        {
            "names": [
                {
                    "name": "torch",
                    "asname": null,
                    "node_type": "alias"
                }
            ],
            "node_type": "Import"
        },
        {
            "targets": [
                {
                    "id": "data",
                    "ctx": {
                        "node_type": "Store"
                    },
                    "node_type": "Name"
                }
            ],
            "value": {
                "elt": {
                    "elts": [
                        {
                            "func": {
                                "value": {
                                    "id": "torch",
                                    "ctx": {
                                        "node_type": "Load"
                                    },
                                    "node_type": "Name"
                                },
                                "attr": "rand",
                                "ctx": {
                                    "node_type": "Load"
                                },
                                "node_type": "Attribute"
                            },
                            "args": [
                                {
                                    "value": 16,
                                    "kind": null,
                                    "node_type": "Constant"
                                },
                                {
                                    "value": 3,
                                    "kind": null,
                                    "node_type": "Constant"
                                },
                                {
                                    "value": 32,
                                    "kind": null,
                                    "node_type": "Constant"
                                },
                                {
                                    "value": 32,
                                    "kind": null,
                                    "node_type": "Constant"
                                }
                            ],
                            "keywords": [],
                            "node_type": "Call"
                        },
                        {
                            "func": {
                                "value": {
                                    "id": "torch",
                                    "ctx": {
                                        "node_type": "Load"
                                    },
                                    "node_type": "Name"
                                },
                                "attr": "rand",
                                "ctx": {
                                    "node_type": "Load"
                                },
                                "node_type": "Attribute"
                            },
                            "args": [
                                {
                                    "value": 1,
                                    "kind": null,
                                    "node_type": "Constant"
                                }
                            ],
                            "keywords": [],
                            "node_type": "Call"
                        }
                    ],
                    "ctx": {
                        "node_type": "Load"
                    },
                    "node_type": "Tuple"
                },
                "generators": [
                    {
                        "target": {
                            "id": "_",
                            "ctx": {
                                "node_type": "Store"
                            },
                            "node_type": "Name"
                        },
                        "iter": {
                            "func": {
                                "id": "range",
                                "ctx": {
                                    "node_type": "Load"
                                },
                                "node_type": "Name"
                            },
                            "args": [
                                {
                                    "value": 100,
                                    "kind": null,
                                    "node_type": "Constant"
                                }
                            ],
                            "keywords": [],
                            "node_type": "Call"
                        },
                        "ifs": [],
                        "is_async": 0,
                        "node_type": "comprehension"
                    }
                ],
                "node_type": "ListComp"
            },
            "type_comment": null,
            "node_type": "Assign"
        },
        {
            "targets": [
                {
                    "id": "W",
                    "ctx": {
                        "node_type": "Store"
                    },
                    "node_type": "Name"
                }
            ],
            "value": {
                "func": {
                    "value": {
                        "id": "torch",
                        "ctx": {
                            "node_type": "Load"
                        },
                        "node_type": "Name"
                    },
                    "attr": "rand",
                    "ctx": {
                        "node_type": "Load"
                    },
                    "node_type": "Attribute"
                },
                "args": [
                    {
                        "value": 31,
                        "kind": null,
                        "node_type": "Constant"
                    },
                    {
                        "value": 32,
                        "kind": null,
                        "node_type": "Constant"
                    }
                ],
                "keywords": [],
                "node_type": "Call"
            },
            "type_comment": null,
            "node_type": "Assign"
        },
        {
            "targets": [
                {
                    "id": "total",
                    "ctx": {
                        "node_type": "Store"
                    },
                    "node_type": "Name"
                }
            ],
            "value": {
                "func": {
                    "value": {
                        "id": "torch",
                        "ctx": {
                            "node_type": "Load"
                        },
                        "node_type": "Name"
                    },
                    "attr": "zeros",
                    "ctx": {
                        "node_type": "Load"
                    },
                    "node_type": "Attribute"
                },
                "args": [
                    {
                        "value": 32,
                        "kind": null,
                        "node_type": "Constant"
                    },
                    {
                        "value": 32,
                        "kind": null,
                        "node_type": "Constant"
                    }
                ],
                "keywords": [],
                "node_type": "Call"
            },
            "type_comment": null,
            "node_type": "Assign"
        },
        {
            "target": {
                "elts": [
                    {
                        "id": "inputs",
                        "ctx": {
                            "node_type": "Store"
                        },
                        "node_type": "Name"
                    },
                    {
                        "id": "labels",
                        "ctx": {
                            "node_type": "Store"
                        },
                        "node_type": "Name"
                    }
                ],
                "ctx": {
                    "node_type": "Store"
                },
                "node_type": "Tuple"
            },
            "iter": {
                "id": "data",
                "ctx": {
                    "node_type": "Load"
                },
                "node_type": "Name"
            },
            "body": [
                {
                    "targets": [
                        {
                            "id": "x",
                            "ctx": {
                                "node_type": "Store"
                            },
                            "node_type": "Name"
                        }
                    ],
                    "value": {
                        "left": {
                            "id": "W",
                            "ctx": {
                                "node_type": "Load"
                            },
                            "node_type": "Name"
                        },
                        "op": {
                            "node_type": "MatMult"
                        },
                        "right": {
                            "id": "inputs",
                            "ctx": {
                                "node_type": "Load"
                            },
                            "node_type": "Name"
                        },
                        "node_type": "BinOp"
                    },
                    "type_comment": null,
                    "node_type": "Assign"
                },
                {
                    "targets": [
                        {
                            "id": "x",
                            "ctx": {
                                "node_type": "Store"
                            },
                            "node_type": "Name"
                        }
                    ],
                    "value": {
                        "left": {
                            "id": "inputs",
                            "ctx": {
                                "node_type": "Load"
                            },
                            "node_type": "Name"
                        },
                        "op": {
                            "node_type": "Sub"
                        },
                        "right": {
                            "id": "labels",
                            "ctx": {
                                "node_type": "Load"
                            },
                            "node_type": "Name"
                        },
                        "node_type": "BinOp"
                    },
                    "type_comment": null,
                    "node_type": "Assign"
                },
                {
                    "targets": [
                        {
                            "id": "total",
                            "ctx": {
                                "node_type": "Store"
                            },
                            "node_type": "Name"
                        }
                    ],
                    "value": {
                        "left": {
                            "id": "total",
                            "ctx": {
                                "node_type": "Load"
                            },
                            "node_type": "Name"
                        },
                        "op": {
                            "node_type": "Add"
                        },
                        "right": {
                            "id": "x",
                            "ctx": {
                                "node_type": "Load"
                            },
                            "node_type": "Name"
                        },
                        "node_type": "BinOp"
                    },
                    "type_comment": null,
                    "node_type": "Assign"
                }
            ],
            "orelse": [],
            "type_comment": null,
            "node_type": "For"
        }
    ],
    "type_ignores": [],
    "node_type": "Module"
}